zhenxun_plugin_chatgpt/__init__.py
zhenxun_plugin_chatgpt/chatgpt.py
zhenxun_plugin_chatgpt/config.py
zhenxun_plugin_chatgpt/data.py
zhenxun_plugin_chatgpt/utils.py
zhenxun_plugin_chatgpt-0.7.4.dist-info/LICENSE
zhenxun_plugin_chatgpt-0.7.4.dist-info/METADATA
zhenxun_plugin_chatgpt-0.7.4.dist-info/WHEEL
zhenxun_plugin_chatgpt-0.7.4.dist-info/RECORD
