Metadata-Version: 2.1
Name: zhenxun-plugin-chatgpt
Version: 0.7.4
Summary: zhenxun plugin for AI chat
License: MIT
Author: INSide_734
Author-email: 3217962725@qq.com
Requires-Python: >=3.9,<4.0
Classifier: License :: OSI Approved :: MIT License
Classifier: Programming Language :: Python :: 3
Classifier: Programming Language :: Python :: 3.9
Classifier: Programming Language :: Python :: 3.10
Classifier: Programming Language :: Python :: 3.11
Requires-Dist: OpenAIAuth (>=0.3.2,<0.4.0)
Requires-Dist: nonebot-plugin-htmlrender (>=0.2.0.3,<0.3.0.0)
